README.md
setup.py
AutoPackaging/__init__.py
AutoPackaging.egg-info/PKG-INFO
AutoPackaging.egg-info/SOURCES.txt
AutoPackaging.egg-info/dependency_links.txt
AutoPackaging.egg-info/top_level.txt