Metadata-Version: 2.1
Name: AutoPackaging
Version: 0.0.1
Summary: Create your packages the easiest way, automaticaly!
Home-page: UNKNOWN
Author: Rafael Rayes
Author-email: rafa@rayes.com.br
License: UNKNOWN
Platform: UNKNOWN
Classifier: Programming Language :: Python :: 3
Classifier: License :: OSI Approved :: MIT License
Classifier: Operating System :: OS Independent
